aws_insurancelake_etl-4.2.4.dist-info/licenses/LICENSE
lib/__init__.py
lib/athena_helper_stack.py
lib/athena_workgroup_stack.py
lib/code_commit_stack.py
lib/configuration.py
lib/data_lake_consumer_stack.py
lib/dynamodb_stack.py
lib/glue_buckets_stack.py
lib/glue_jobs_stack.py
lib/glue_stack.py
lib/pipeline_deploy_stage.py
lib/pipeline_stack.py
lib/stack_import_helper.py
lib/step_functions_stack.py
lib/tagging.py
test/__init__.py
test/boto_mocking_helper.py
test/glue_job_mocking_helper.py
test/glue_job_mocking_helper_stub.py
test/test_athena_helper_stack.py
test/test_athena_workgroup_stack.py
test/test_codecommit_stack.py
test/test_configuration.py
test/test_custom_mapping.py
test/test_data_lake_consumer_stack.py
test/test_datalineage.py
test/test_dataquery.py
test/test_datatransform_dataprotection.py
test/test_datatransform_lookup.py
test/test_datatransform_misc.py
test/test_datatransform_premium.py
test/test_datatransform_stringmanipulation.py
test/test_datatransform_structureddata.py
test/test_datatransform_typeconversion.py
test/test_dynamodb_stack.py
test/test_etl_cleanse_to_consume.py
test/test_etl_collect_to_cleanse.py
test/test_etl_consume_entity_match.py
test/test_etl_job_auditor.py
test/test_glue_buckets_stack.py
test/test_glue_catalog_helpers.py
test/test_glue_jobs_stack.py
test/test_glue_stack.py
test/test_pipeline_stack.py
test/test_stack_import_helper.py
test/test_state_machine_trigger.py
test/test_step_functions_stack.py
test/test_tagging.py
aws_insurancelake_etl-4.2.4.dist-info/METADATA
aws_insurancelake_etl-4.2.4.dist-info/WHEEL
aws_insurancelake_etl-4.2.4.dist-info/top_level.txt
aws_insurancelake_etl-4.2.4.dist-info/RECORD
