Metadata-Version: 2.4
Name: aws-insurancelake-etl
Version: 4.2.4
Summary: A CDK Python app for deploying ETL jobs that operate data pipelines for InsuranceLake in AWS
Home-page: https://github.com/aws-samples/aws-insurancelake-etl
Author: Cory Visi <cvisi@amazon.com>, Ratnadeep Bardhan Roy <rdbroy@amazon.com>, George Gallo <geogallo@amazon.com>, Jose Guay <jrguay@amazon.com>, Isaiah Grant <igrant@2ndwatch.com>, Ravi Itha <itharav@amazon.com>, Zahid Muhammad Ali <zhidli@amazon.com>
License: MIT-0
Keywords: aws-insurancelake-etl aws cdk insurance datalake etl glue spark python pyspark
Classifier: Development Status :: 4 - Beta
Classifier: Intended Audience :: Developers
Classifier: Programming Language :: JavaScript
Classifier: Programming Language :: Python :: 3 :: Only
Classifier: Programming Language :: Python :: 3.9
Classifier: Programming Language :: Python :: 3.10
Classifier: Programming Language :: Python :: 3.11
Classifier: Programming Language :: Python :: 3.12
Classifier: Topic :: Software Development :: Code Generators
Classifier: Topic :: Utilities
Classifier: Typing :: Typed
Requires-Python: >=3.9
License-File: LICENSE
Requires-Dist: aws-cdk-lib>=2.80.0
Requires-Dist: constructs>=10.1.0
Dynamic: author
Dynamic: classifier
Dynamic: description
Dynamic: description-content-type
Dynamic: home-page
Dynamic: keywords
Dynamic: license
Dynamic: license-file
Dynamic: requires-dist
Dynamic: requires-python
Dynamic: summary
